[
  {
    "source": "twitter",
    "id": "1240582639830122497",
    "username": "Yatuu",
    "likes": 675,
    "originalImage": "https://pbs.twimg.com/media/ETdtpjXXQAYh2QT.jpg",
    "avatarImage": "https://pbs.twimg.com/profile_images/448506804595470336/DU--oi5U_normal.jpeg",
    "date": "2020-03-19T11:15:24.000+01:00",
    "imageWidth": 1200,
    "imageHeight": 848
  },
  {
    "source": "twitter",
    "id": "1240557566981296129",
    "username": "misshollyslair",
    "likes": 521,
    "originalImage": "https://pbs.twimg.com/media/ETdXfjMXQAAIWUw.jpg",
    "avatarImage": "https://pbs.twimg.com/profile_images/1222962730803630081/Z76B9GOc_normal.jpg",
    "date": "2020-03-19T09:35:47.000+01:00",
    "imageWidth": 1029,
    "imageHeight": 708
  },
  {
    "source": "twitter",
    "id": "1240755769987018770",
    "username": "dineuh1",
    "likes": 493,
    "originalImage": "https://pbs.twimg.com/media/ETgMjrNWAAEcGUZ.jpg",
    "avatarImage": "https://pbs.twimg.com/profile_images/1223284245130567681/Sz1IGCku_normal.jpg",
    "date": "2020-03-19T22:43:22.000+01:00",
    "imageWidth": 1200,
    "imageHeight": 644
  },
  {
    "source": "twitter",
    "id": "1240674567183613959",
    "username": "ChocoClemence",
    "likes": 181,
    "originalImage": "https://pbs.twimg.com/media/ETfC3LuX0AUzvZi.jpg",
    "avatarImage": "https://pbs.twimg.com/profile_images/1185189407915155457/xu4nTpJU_normal.jpg",
    "date": "2020-03-19T17:20:42.000+01:00",
    "imageWidth": 1200,
    "imageHeight": 797
  },
  {
    "source": "twitter",
    "id": "1240712849472630784",
    "username": "yohansacre",
    "likes": 133,
    "originalImage": "https://pbs.twimg.com/media/ETflwTuXYAI08Ku.jpg",
    "avatarImage": "https://pbs.twimg.com/profile_images/988002771306713089/8IVulcAS_normal.jpg",
    "date": "2020-03-19T19:52:49.000+01:00",
    "imageWidth": 1199,
    "imageHeight": 681
  },
  {
    "source": "twitter",
    "id": "1240641254632894466",
    "username": "Tamagauchiste",
    "likes": 100,
    "originalImage": "https://pbs.twimg.com/media/ETekFflWsAIoy2J.jpg",
    "avatarImage": "https://pbs.twimg.com/profile_images/1229049503933747201/cSc8Acfo_normal.jpg",
    "date": "2020-03-19T15:08:19.000+01:00",
    "imageWidth": 1200,
    "imageHeight": 689
  },
  {
    "source": "twitter",
    "id": "1240714628382044160",
    "username": "Emilien_NXT",
    "likes": 83,
    "originalImage": "https://pbs.twimg.com/media/ETfnXwrWkAAjZ9A.jpg",
    "avatarImage": "https://pbs.twimg.com/profile_images/1126619140066881537/2ayYjJ83_normal.png",
    "date": "2020-03-19T19:59:53.000+01:00",
    "imageWidth": 1080,
    "imageHeight": 1080
  },
  {
    "source": "twitter",
    "id": "1240666480255139840",
    "username": "DeadlegCyborg",
    "likes": 63,
    "originalImage": "https://pbs.twimg.com/media/ETe7laoX0AEzwkZ.jpg",
    "avatarImage": "https://pbs.twimg.com/profile_images/1191786744204726272/1Ac7_PKt_normal.jpg",
    "date": "2020-03-19T16:48:34.000+01:00",
    "imageWidth": 1029,
    "imageHeight": 708
  },
  {
    "source": "twitter",
    "id": "1240760757383544833",
    "username": "AngiesJunk",
    "likes": 62,
    "originalImage": "https://pbs.twimg.com/media/ETgRUVhWsAkyNOh.jpg",
    "avatarImage": "https://pbs.twimg.com/profile_images/1169163339366375424/48K2NjxL_normal.jpg",
    "date": "2020-03-19T23:03:11.000+01:00",
    "imageWidth": 781,
    "imageHeight": 419
  },
  {
    "source": "twitter",
    "id": "1240712736574767110",
    "username": "adoubidouu",
    "likes": 58,
    "originalImage": "https://pbs.twimg.com/media/ETflp5jWkAA6Vbt.jpg",
    "avatarImage": "https://pbs.twimg.com/profile_images/848463028047810560/2YOisYZR_normal.jpg",
    "date": "2020-03-19T19:52:22.000+01:00",
    "imageWidth": 750,
    "imageHeight": 412
  },
  {
    "source": "twitter",
    "id": "1240695166119211010",
    "username": "GrisCiel3",
    "likes": 53,
    "originalImage": "https://pbs.twimg.com/media/ETfU0XCXsAALzco.jpg",
    "avatarImage": "https://pbs.twimg.com/profile_images/1214845366610407424/qQErLTE0_normal.jpg",
    "date": "2020-03-19T18:42:33.000+01:00",
    "imageWidth": 1200,
    "imageHeight": 668
  },
  {
    "source": "twitter",
    "id": "1240719875477307392",
    "username": "HeyCrevisse",
    "likes": 43,
    "originalImage": "https://pbs.twimg.com/media/ETfqd2rXYAIKWrc.jpg",
    "avatarImage": "https://pbs.twimg.com/profile_images/1209435547653091328/GgxcTiQs_normal.jpg",
    "date": "2020-03-19T20:20:44.000+01:00",
    "imageWidth": 1199,
    "imageHeight": 650
  },
  {
    "source": "twitter",
    "id": "1240700307908128769",
    "username": "alxisvlr",
    "likes": 39,
    "originalImage": "https://pbs.twimg.com/media/ETfaSe3WsAARPT2.jpg",
    "avatarImage": "https://pbs.twimg.com/profile_images/1209970523670818822/xAzSausQ_normal.jpg",
    "date": "2020-03-19T19:02:59.000+01:00",
    "imageWidth": 1200,
    "imageHeight": 900
  },
  {
    "source": "twitter",
    "id": "1240714044505554951",
    "username": "Yusi9406",
    "likes": 38,
    "originalImage": "https://pbs.twimg.com/media/ETfmm2qWoAIJfoy.jpg",
    "avatarImage": "https://pbs.twimg.com/profile_images/842096960505053184/qYURhxrd_normal.jpg",
    "date": "2020-03-19T19:57:34.000+01:00",
    "imageWidth": 1199,
    "imageHeight": 644
  },
  {
    "source": "twitter",
    "id": "1240566398784548864",
    "username": "Emisiala",
    "likes": 36,
    "originalImage": "https://pbs.twimg.com/media/ETdgicNXgAApTo0.jpg",
    "avatarImage": "https://pbs.twimg.com/profile_images/1107299218513895425/uWrnRnpG_normal.jpg",
    "date": "2020-03-19T10:10:52.000+01:00",
    "imageWidth": 1024,
    "imageHeight": 704
  },
  {
    "source": "twitter",
    "id": "1240749931549376517",
    "username": "Ellehar_",
    "likes": 33,
    "originalImage": "https://pbs.twimg.com/media/ETgHer5XQAEt8QN.jpg",
    "avatarImage": "https://pbs.twimg.com/profile_images/902642871873937408/8KKKU_Xz_normal.jpg",
    "date": "2020-03-19T22:20:10.000+01:00",
    "imageWidth": 1199,
    "imageHeight": 654
  },
  {
    "source": "twitter",
    "id": "1240689921343381508",
    "username": "besswinty",
    "likes": 31,
    "originalImage": "https://pbs.twimg.com/media/ETfQenoWAAAYaot.jpg",
    "avatarImage": "https://pbs.twimg.com/profile_images/855732191682326528/ZUuRGpno_normal.jpg",
    "date": "2020-03-19T18:21:42.000+01:00",
    "imageWidth": 1200,
    "imageHeight": 682
  },
  {
    "source": "twitter",
    "id": "1240707215943761921",
    "username": "SolenePllt",
    "likes": 28,
    "originalImage": "https://pbs.twimg.com/media/ETfgcR8XgAAf7kQ.jpg",
    "avatarImage": "https://pbs.twimg.com/profile_images/1221516845406203905/X-W-b2g3_normal.jpg",
    "date": "2020-03-19T19:30:26.000+01:00",
    "imageWidth": 1200,
    "imageHeight": 848
  },
  {
    "source": "twitter",
    "id": "1240655637031288839",
    "username": "ArnaudLeRoux",
    "likes": 26,
    "originalImage": "https://pbs.twimg.com/media/ETexuQGWoAQrDgW.jpg",
    "avatarImage": "https://pbs.twimg.com/profile_images/576349216991109121/tViGlSId_normal.jpeg",
    "date": "2020-03-19T16:05:28.000+01:00",
    "imageWidth": 900,
    "imageHeight": 1200
  },
  {
    "source": "twitter",
    "id": "1240628574241128448",
    "username": "jeancomebd",
    "likes": 25,
    "originalImage": "https://pbs.twimg.com/media/ETeYwZfXgAA_QQH.jpg",
    "avatarImage": "https://pbs.twimg.com/profile_images/982175887889022981/SM6COkUe_normal.jpg",
    "date": "2020-03-19T14:17:56.000+01:00",
    "imageWidth": 1200,
    "imageHeight": 724
  },
  {
    "source": "twitter",
    "id": "1240627853672185856",
    "username": "hathoryt",
    "likes": 25,
    "originalImage": "https://pbs.twimg.com/media/ETeYdFfX0AAws9D.jpg",
    "avatarImage": "https://pbs.twimg.com/profile_images/1237829039613718530/OlV80pLq_normal.jpg",
    "date": "2020-03-19T14:15:04.000+01:00",
    "imageWidth": 1199,
    "imageHeight": 821
  },
  {
    "source": "twitter",
    "id": "1240750283766083584",
    "username": "LuluBTX",
    "likes": 22,
    "originalImage": "https://pbs.twimg.com/media/ETgHyJaWkAEqw9W.jpg",
    "avatarImage": "https://pbs.twimg.com/profile_images/763309013257904128/EgicI2zs_normal.jpg",
    "date": "2020-03-19T22:21:34.000+01:00",
    "imageWidth": 1200,
    "imageHeight": 1122
  },
  {
    "source": "twitter",
    "id": "1240697222418722816",
    "username": "mllecarofla",
    "likes": 22,
    "originalImage": "https://pbs.twimg.com/media/ETfXi36XsAA99DZ.jpg",
    "avatarImage": "https://pbs.twimg.com/profile_images/1240986224904622081/j-Ys5F0g_normal.jpg",
    "date": "2020-03-19T18:50:43.000+01:00",
    "imageWidth": 1200,
    "imageHeight": 704
  },
  {
    "source": "twitter",
    "id": "1240576176256692224",
    "username": "GaelAnjale",
    "likes": 22,
    "originalImage": "https://pbs.twimg.com/media/ETdpYNSWsAEDyl2.jpg",
    "avatarImage": "https://pbs.twimg.com/profile_images/1056858490759774208/jpCwWlpG_normal.jpg",
    "date": "2020-03-19T10:49:43.000+01:00",
    "imageWidth": 1181,
    "imageHeight": 813
  },
  {
    "source": "twitter",
    "id": "1240622549920342016",
    "username": "Mercvtivs",
    "likes": 21,
    "originalImage": "https://pbs.twimg.com/media/ETeTU-7X0AEQuyA.jpg",
    "avatarImage": "https://pbs.twimg.com/profile_images/1467981800/avatarmanga_normal.jpg",
    "date": "2020-03-19T13:54:00.000+01:00",
    "imageWidth": 1200,
    "imageHeight": 900
  },
  {
    "source": "twitter",
    "id": "1240743292335206418",
    "username": "YaelCdf",
    "likes": 20,
    "originalImage": "https://pbs.twimg.com/media/ETgBcDNXkAEVFu8.jpg",
    "avatarImage": "https://pbs.twimg.com/profile_images/1240742816503996417/g0BBUbCs_normal.jpg",
    "date": "2020-03-19T21:53:47.000+01:00",
    "imageWidth": 1200,
    "imageHeight": 650
  },
  {
    "source": "twitter",
    "id": "1240705136105644032",
    "username": "Laurent_Potelle",
    "likes": 19,
    "originalImage": "https://pbs.twimg.com/media/ETfeVkoXsAAmkJu.png",
    "avatarImage": "https://pbs.twimg.com/profile_images/1227306705169657858/IqmFCkqU_normal.jpg",
    "date": "2020-03-19T19:22:10.000+01:00",
    "imageWidth": 680,
    "imageHeight": 468
  },
  {
    "source": "twitter",
    "id": "1240690538036129792",
    "username": "_aldaline_",
    "likes": 18,
    "originalImage": "https://pbs.twimg.com/media/ETfRcm8XQAAgSki.jpg",
    "avatarImage": "https://pbs.twimg.com/profile_images/1200869520602259467/wHL44S5g_normal.jpg",
    "date": "2020-03-19T18:24:09.000+01:00",
    "imageWidth": 1024,
    "imageHeight": 539
  },
  {
    "source": "twitter",
    "id": "1240576355449921536",
    "username": "afonfonfon",
    "likes": 18,
    "originalImage": "https://pbs.twimg.com/media/ETdpndaWkAE84Ib.jpg",
    "avatarImage": "https://pbs.twimg.com/profile_images/1214147445346553856/JL74AGdx_normal.jpg",
    "date": "2020-03-19T10:50:26.000+01:00",
    "imageWidth": 1200,
    "imageHeight": 840
  },
  {
    "source": "twitter",
    "id": "1240687411937464320",
    "username": "eyevertclair",
    "likes": 17,
    "originalImage": "https://pbs.twimg.com/media/ETfOl2DXkAMbx2p.jpg",
    "avatarImage": "https://pbs.twimg.com/profile_images/701474288453492736/IBH4IJt7_normal.jpg",
    "date": "2020-03-19T18:11:44.000+01:00",
    "imageWidth": 1199,
    "imageHeight": 848
  },
  {
    "source": "twitter",
    "id": "1240575513153994759",
    "username": "Poutre45",
    "likes": 15,
    "originalImage": "https://pbs.twimg.com/media/ETdo1VeXQAAOY6D.jpg",
    "avatarImage": "https://pbs.twimg.com/profile_images/1213148343402147843/Gekes3n__normal.jpg",
    "date": "2020-03-19T10:47:05.000+01:00",
    "imageWidth": 1024,
    "imageHeight": 558
  },
  {
    "source": "twitter",
    "id": "1240619010762440706",
    "username": "Meskinapadme",
    "likes": 14,
    "originalImage": "https://pbs.twimg.com/media/ETeQTvQXkAAdnGF.jpg",
    "avatarImage": "https://pbs.twimg.com/profile_images/1211636560178950144/0N2sx3tF_normal.jpg",
    "date": "2020-03-19T13:39:56.000+01:00",
    "imageWidth": 1012,
    "imageHeight": 531
  },
  {
    "source": "twitter",
    "id": "1240555237196337152",
    "username": "AurlienGilles",
    "likes": 14,
    "originalImage": "https://pbs.twimg.com/media/ETdWYoCXYAERDbX.jpg",
    "avatarImage": "https://pbs.twimg.com/profile_images/3601920766/004e43942baec481495304515c398f01_normal.jpeg",
    "date": "2020-03-19T09:26:31.000+01:00",
    "imageWidth": 1200,
    "imageHeight": 760
  },
  {
    "source": "twitter",
    "id": "1240708384480882688",
    "username": "KikaChuuu",
    "likes": 13,
    "originalImage": "https://pbs.twimg.com/media/ETff1goWAAADAWB.jpg",
    "avatarImage": "https://pbs.twimg.com/profile_images/1112460903402881024/AQNZ83ZO_normal.jpg",
    "date": "2020-03-19T19:35:04.000+01:00",
    "imageWidth": 1200,
    "imageHeight": 708
  },
  {
    "source": "twitter",
    "id": "1240682149600206849",
    "username": "MadDuFutur",
    "likes": 13,
    "originalImage": "https://pbs.twimg.com/media/ETfIs6fWAAEMuy_.jpg",
    "avatarImage": "https://pbs.twimg.com/profile_images/866678585335181312/91O9Z8Tf_normal.jpg",
    "date": "2020-03-19T17:50:49.000+01:00",
    "imageWidth": 1200,
    "imageHeight": 760
  },
  {
    "source": "twitter",
    "id": "1240582749834170369",
    "username": "Domydom",
    "likes": 13,
    "originalImage": "https://pbs.twimg.com/media/ETdvZLTX0AA0D_E.jpg",
    "avatarImage": "https://pbs.twimg.com/profile_images/2393722055/gyekh8csdudew7fz7rtb_normal.gif",
    "date": "2020-03-19T11:15:51.000+01:00",
    "imageWidth": 1024,
    "imageHeight": 588
  },
  {
    "source": "twitter",
    "id": "1240683755922165762",
    "username": "CrearteniaV",
    "likes": 12,
    "originalImage": "https://pbs.twimg.com/media/ETfLOKuX0AAwT5h.jpg",
    "avatarImage": "https://pbs.twimg.com/profile_images/1227971213374431232/cr9sIfMq_normal.jpg",
    "date": "2020-03-19T17:57:12.000+01:00",
    "imageWidth": 1200,
    "imageHeight": 848
  },
  {
    "source": "twitter",
    "id": "1240593288601755649",
    "username": "coalsprincess",
    "likes": 12,
    "originalImage": "https://pbs.twimg.com/media/ETd42L8XsAIs2nb.jpg",
    "avatarImage": "https://pbs.twimg.com/profile_images/1236084948186148865/4yWx9bnm_normal.jpg",
    "date": "2020-03-19T11:57:43.000+01:00",
    "imageWidth": 1200,
    "imageHeight": 900
  },
  {
    "source": "twitter",
    "id": "1240594586801668099",
    "username": "IDBOOX",
    "likes": 12,
    "originalImage": "https://pbs.twimg.com/media/ETd561wX0AM06XZ.jpg",
    "avatarImage": "https://pbs.twimg.com/profile_images/450575323109675009/PEakP0FF_normal.jpeg",
    "date": "2020-03-19T12:02:53.000+01:00",
    "imageWidth": 1200,
    "imageHeight": 844
  },
  {
    "source": "twitter",
    "id": "1240590897424863233",
    "username": "IMTLilleDouai",
    "likes": 12,
    "originalImage": "https://pbs.twimg.com/media/ETd20rYXQAQaerj.jpg",
    "avatarImage": "https://pbs.twimg.com/profile_images/791525514188029952/NV4GrHau_normal.jpg",
    "date": "2020-03-19T11:48:13.000+01:00",
    "imageWidth": 1199,
    "imageHeight": 643
  },
  {
    "source": "twitter",
    "id": "1240461855421804550",
    "username": "Tamagauchiste",
    "likes": 12,
    "originalImage": "https://pbs.twimg.com/media/ETcBOuCXQAAeRN4.jpg",
    "avatarImage": "https://pbs.twimg.com/profile_images/1229049503933747201/cSc8Acfo_normal.jpg",
    "date": "2020-03-19T03:15:27.000+01:00",
    "imageWidth": 1200,
    "imageHeight": 710
  },
  {
    "source": "twitter",
    "id": "1240710376364244992",
    "username": "Lemondedaxel",
    "likes": 11,
    "originalImage": "https://pbs.twimg.com/media/ETfjWShX0AAgfnj.jpg",
    "avatarImage": "https://pbs.twimg.com/profile_images/1189161520724357120/YdqKZ3_U_normal.jpg",
    "date": "2020-03-19T19:42:59.000+01:00",
    "imageWidth": 1200,
    "imageHeight": 636
  },
  {
    "source": "twitter",
    "id": "1240602340849332231",
    "username": "MokaCeless",
    "likes": 11,
    "originalImage": "https://pbs.twimg.com/media/ETeBMKnWAAAMi20.jpg",
    "avatarImage": "https://pbs.twimg.com/profile_images/1238238535452364800/mPC7C357_normal.jpg",
    "date": "2020-03-19T12:33:41.000+01:00",
    "imageWidth": 1200,
    "imageHeight": 660
  },
  {
    "source": "twitter",
    "id": "1240549798299779072",
    "username": "AurlienGilles",
    "likes": 11,
    "originalImage": "https://pbs.twimg.com/media/ETdRJrxWsAAyvsT.jpg",
    "avatarImage": "https://pbs.twimg.com/profile_images/3601920766/004e43942baec481495304515c398f01_normal.jpeg",
    "date": "2020-03-19T09:04:54.000+01:00",
    "imageWidth": 1200,
    "imageHeight": 760
  },
  {
    "source": "twitter",
    "id": "1240641654857613315",
    "username": "DavArtNow",
    "likes": 10,
    "originalImage": "https://pbs.twimg.com/media/ETek_SNXkAAsFk6.jpg",
    "avatarImage": "https://pbs.twimg.com/profile_images/1157096941714411520/nlvl9SNW_normal.png",
    "date": "2020-03-19T15:09:55.000+01:00",
    "imageWidth": 793,
    "imageHeight": 542
  },
  {
    "source": "twitter",
    "id": "1240527153608998919",
    "username": "InesDucommun",
    "likes": 8,
    "originalImage": "https://pbs.twimg.com/media/ETc80ttWkAsNGM5.jpg",
    "avatarImage": "https://pbs.twimg.com/profile_images/621267784132132864/hFVvLIg0_normal.jpg",
    "date": "2020-03-19T07:34:55.000+01:00",
    "imageWidth": 640,
    "imageHeight": 475
  },
  {
    "source": "twitter",
    "id": "1240753264871772160",
    "username": "korriganne_",
    "likes": 7,
    "originalImage": "https://pbs.twimg.com/media/ETgKggnWAAEvBe0.jpg",
    "avatarImage": "https://pbs.twimg.com/profile_images/1236411259018514432/n0s92SO8_normal.jpg",
    "date": "2020-03-19T22:33:25.000+01:00",
    "imageWidth": 959,
    "imageHeight": 960
  },
  {
    "source": "twitter",
    "id": "1240742189782761482",
    "username": "YaelCdf",
    "likes": 7,
    "originalImage": "https://pbs.twimg.com/media/ETgAcAUWsAAIwiT.jpg",
    "avatarImage": "https://pbs.twimg.com/profile_images/1240742816503996417/g0BBUbCs_normal.jpg",
    "date": "2020-03-19T21:49:24.000+01:00",
    "imageWidth": 1200,
    "imageHeight": 650
  },
  {
    "source": "twitter",
    "id": "1240714010401464320",
    "username": "lascar_pacap",
    "likes": 7,
    "originalImage": "https://pbs.twimg.com/media/ETfmAJvXsAQHqrH.jpg",
    "avatarImage": "https://pbs.twimg.com/profile_images/1195139145083097095/hGhO-rkZ_normal.jpg",
    "date": "2020-03-19T19:57:26.000+01:00",
    "imageWidth": 1200,
    "imageHeight": 675
  },
  {
    "source": "twitter",
    "id": "1240582466483740677",
    "username": "Domydom",
    "likes": 7,
    "originalImage": "https://pbs.twimg.com/media/ETdvHHHXgAAsJ7-.jpg",
    "avatarImage": "https://pbs.twimg.com/profile_images/2393722055/gyekh8csdudew7fz7rtb_normal.gif",
    "date": "2020-03-19T11:14:43.000+01:00",
    "imageWidth": 1200,
    "imageHeight": 690
  },
  {
    "source": "twitter",
    "id": "1240703039440371712",
    "username": "Tovenesto",
    "likes": 6,
    "originalImage": "https://pbs.twimg.com/media/ETfc1HuXYAUEFS7.jpg",
    "avatarImage": "https://pbs.twimg.com/profile_images/923595552075538432/LO8-GwT0_normal.jpg",
    "date": "2020-03-19T19:13:50.000+01:00",
    "imageWidth": 1008,
    "imageHeight": 558
  },
  {
    "source": "twitter",
    "id": "1240687419243917313",
    "username": "EikonaI",
    "likes": 6,
    "originalImage": "https://pbs.twimg.com/media/ETfOnwqXQAU7JOI.jpg",
    "avatarImage": "https://pbs.twimg.com/profile_images/1240667953374408704/xGYyG2gW_normal.jpg",
    "date": "2020-03-19T18:11:46.000+01:00",
    "imageWidth": 1200,
    "imageHeight": 863
  },
  {
    "source": "twitter",
    "id": "1240721122934632448",
    "username": "FranchouC",
    "likes": 5,
    "originalImage": "https://pbs.twimg.com/media/ETftEQaWoAYezFL.jpg",
    "avatarImage": "https://pbs.twimg.com/profile_images/1106621608200937472/wRRH9-Or_normal.jpg",
    "date": "2020-03-19T20:25:41.000+01:00",
    "imageWidth": 940,
    "imageHeight": 529
  },
  {
    "source": "twitter",
    "id": "1240672614663716864",
    "username": "IlanWroblewski",
    "likes": 5,
    "originalImage": "https://pbs.twimg.com/media/ETfBHNyX0AIiX6x.jpg",
    "avatarImage": "https://pbs.twimg.com/profile_images/1233041068523970562/GbKa9uK7_normal.jpg",
    "date": "2020-03-19T17:12:56.000+01:00",
    "imageWidth": 1200,
    "imageHeight": 645
  },
  {
    "source": "twitter",
    "id": "1240655340900945920",
    "username": "CatCointe",
    "likes": 5,
    "originalImage": "https://pbs.twimg.com/media/ETexVvBXYAErwvJ.jpg",
    "avatarImage": "https://pbs.twimg.com/profile_images/983697913225375745/TPwaYX6z_normal.jpg",
    "date": "2020-03-19T16:04:18.000+01:00",
    "imageWidth": 797,
    "imageHeight": 476
  },
  {
    "source": "twitter",
    "id": "1240647347530539010",
    "username": "photos_floues",
    "likes": 5,
    "originalImage": "https://pbs.twimg.com/media/ETeqJljX0AMRrhV.jpg",
    "avatarImage": "https://pbs.twimg.com/profile_images/1013328679546613761/sEIEPSJW_normal.jpg",
    "date": "2020-03-19T15:32:32.000+01:00",
    "imageWidth": 1200,
    "imageHeight": 653
  },
  {
    "source": "twitter",
    "id": "1240562624670171137",
    "username": "VersiondO",
    "likes": 5,
    "originalImage": "https://pbs.twimg.com/media/ETddHN-WsAERbZo.jpg",
    "avatarImage": "https://pbs.twimg.com/profile_images/1230945884214525953/-GPKduZq_normal.jpg",
    "date": "2020-03-19T09:55:52.000+01:00",
    "imageWidth": 1200,
    "imageHeight": 826
  },
  {
    "source": "twitter",
    "id": "1240768709423177729",
    "username": "BorisSemeniako",
    "likes": 4,
    "originalImage": "https://pbs.twimg.com/media/ETgYbKnX0AA1u-o.jpg",
    "avatarImage": "https://pbs.twimg.com/profile_images/1111195788795957248/RTzwh-2e_normal.png",
    "date": "2020-03-19T23:34:47.000+01:00",
    "imageWidth": 1000,
    "imageHeight": 554
  },
  {
    "source": "twitter",
    "id": "1240733361255170051",
    "username": "PetitMetalleux",
    "likes": 4,
    "originalImage": "https://pbs.twimg.com/media/ETf1YouXQAENR1s.jpg",
    "avatarImage": "https://pbs.twimg.com/profile_images/1237632308582264832/Mpd7JqwK_normal.jpg",
    "date": "2020-03-19T21:14:19.000+01:00",
    "imageWidth": 1200,
    "imageHeight": 751
  },
  {
    "source": "twitter",
    "id": "1240586565035995142",
    "username": "Jerres12",
    "likes": 4,
    "originalImage": "https://pbs.twimg.com/media/ETdyx5JXgAEufFK.png",
    "avatarImage": "https://pbs.twimg.com/profile_images/1074329354107322369/nVi6eu-g_normal.jpg",
    "date": "2020-03-19T11:31:00.000+01:00",
    "imageWidth": 384,
    "imageHeight": 272
  },
  {
    "source": "twitter",
    "id": "1240554738346864640",
    "username": "Peanut_btr",
    "likes": 4,
    "originalImage": "https://pbs.twimg.com/media/ETdV8IVXgAI8awx.jpg",
    "avatarImage": "https://pbs.twimg.com/profile_images/1241675715239710721/NivkSLwp_normal.jpg",
    "date": "2020-03-19T09:24:32.000+01:00",
    "imageWidth": 1200,
    "imageHeight": 900
  },
  {
    "source": "twitter",
    "id": "1240756733460582407",
    "username": "ben_weeks",
    "likes": 3,
    "originalImage": "https://pbs.twimg.com/media/ETgNoCZXkAA1emG.jpg",
    "avatarImage": "https://pbs.twimg.com/profile_images/924026042037297152/V_OG-jrQ_normal.jpg",
    "date": "2020-03-19T22:47:12.000+01:00",
    "imageWidth": 1200,
    "imageHeight": 640
  },
  {
    "source": "twitter",
    "id": "1240627673854029824",
    "username": "fredfactory",
    "likes": 3,
    "originalImage": "https://pbs.twimg.com/media/ETeYLyVXsAIqRwE.jpg",
    "avatarImage": "https://pbs.twimg.com/profile_images/1239308951033974787/LY4KWR3f_normal.jpg",
    "date": "2020-03-19T14:14:21.000+01:00",
    "imageWidth": 1200,
    "imageHeight": 826
  },
  {
    "source": "twitter",
    "id": "1240618815836295174",
    "username": "AureliliCom",
    "likes": 3,
    "originalImage": "https://pbs.twimg.com/media/ETePb6PWkAE5-3a.jpg",
    "avatarImage": "https://pbs.twimg.com/profile_images/555678683323580416/DvuM8-L5_normal.jpeg",
    "date": "2020-03-19T13:39:09.000+01:00",
    "imageWidth": 1200,
    "imageHeight": 900
  },
  {
    "source": "twitter",
    "id": "1240580938419122176",
    "username": "pinkplxnts",
    "likes": 3,
    "originalImage": "https://pbs.twimg.com/media/ETdtxCTWsAArQUw.jpg",
    "avatarImage": "https://pbs.twimg.com/profile_images/1241695347505848325/d94_rCDu_normal.jpg",
    "date": "2020-03-19T11:08:39.000+01:00",
    "imageWidth": 1200,
    "imageHeight": 900
  },
  {
    "source": "twitter",
    "id": "1240764912399536131",
    "username": "zemoko",
    "likes": 2,
    "originalImage": "https://pbs.twimg.com/media/ETgVGvCWsAk8EG_.jpg",
    "avatarImage": "https://pbs.twimg.com/profile_images/1108097462873538561/r7uqBdoD_normal.png",
    "date": "2020-03-19T23:19:42.000+01:00",
    "imageWidth": 1199,
    "imageHeight": 899
  },
  {
    "source": "twitter",
    "id": "1240757411318829056",
    "username": "Ma_nonMrt",
    "likes": 2,
    "originalImage": "https://pbs.twimg.com/media/ETgOSGjXkAIGsou.jpg",
    "avatarImage": "https://pbs.twimg.com/profile_images/1232305606683435014/bW8jVx2r_normal.jpg",
    "date": "2020-03-19T22:49:53.000+01:00",
    "imageWidth": 1200,
    "imageHeight": 1200
  },
  {
    "source": "twitter",
    "id": "1240717910592696327",
    "username": "Clmncthms",
    "likes": 2,
    "originalImage": "https://pbs.twimg.com/media/ETfqW7qWkAEc7aw.jpg",
    "avatarImage": "https://pbs.twimg.com/profile_images/1240718302986592258/1Oh4yjAS_normal.jpg",
    "date": "2020-03-19T20:12:55.000+01:00",
    "imageWidth": 1080,
    "imageHeight": 810
  },
  {
    "source": "twitter",
    "id": "1240693005511614465",
    "username": "Cazou7",
    "likes": 2,
    "originalImage": "https://pbs.twimg.com/media/ETfTeWxWkAEkmfq.jpg",
    "avatarImage": "https://pbs.twimg.com/profile_images/1241028707885686784/j0bLnn76_normal.jpg",
    "date": "2020-03-19T18:33:58.000+01:00",
    "imageWidth": 1200,
    "imageHeight": 809
  },
  {
    "source": "twitter",
    "id": "1240674617758367745",
    "username": "Lib_Livresque",
    "likes": 2,
    "originalImage": "https://pbs.twimg.com/media/ETfC6EpXgAAU8ID.jpg",
    "avatarImage": "https://pbs.twimg.com/profile_images/908702083515371520/_WDr2AKh_normal.jpg",
    "date": "2020-03-19T17:20:54.000+01:00",
    "imageWidth": 1200,
    "imageHeight": 658
  },
  {
    "source": "twitter",
    "id": "1240658809741348865",
    "username": "erikniells",
    "likes": 2,
    "originalImage": "https://pbs.twimg.com/media/ETe0m83XYAEuc2r.jpg",
    "avatarImage": "https://pbs.twimg.com/profile_images/763062664775872512/3AUt19xy_normal.jpg",
    "date": "2020-03-19T16:18:05.000+01:00",
    "imageWidth": 1200,
    "imageHeight": 825
  },
  {
    "source": "twitter",
    "id": "1240647838561972224",
    "username": "fredfactory",
    "likes": 2,
    "originalImage": "https://pbs.twimg.com/media/ETeqmBYXgAA-1aO.jpg",
    "avatarImage": "https://pbs.twimg.com/profile_images/1239308951033974787/LY4KWR3f_normal.jpg",
    "date": "2020-03-19T15:34:29.000+01:00",
    "imageWidth": 1200,
    "imageHeight": 826
  },
  {
    "source": "twitter",
    "id": "1240646670846754822",
    "username": "MarianaGrepinet",
    "likes": 2,
    "originalImage": "https://pbs.twimg.com/media/ETepkNoWAAA1Cvl.jpg",
    "avatarImage": "https://pbs.twimg.com/profile_images/1167150513391099904/GFg-HwxS_normal.jpg",
    "date": "2020-03-19T15:29:51.000+01:00",
    "imageWidth": 1200,
    "imageHeight": 813
  },
  {
    "source": "twitter",
    "id": "1240628630373511169",
    "username": "maggirepsbfc",
    "likes": 2,
    "originalImage": "https://pbs.twimg.com/media/ETeZHrmWsAIB8lY.jpg",
    "avatarImage": "https://pbs.twimg.com/profile_images/1232289379676237825/_0CU0SR1_normal.jpg",
    "date": "2020-03-19T14:18:09.000+01:00",
    "imageWidth": 1200,
    "imageHeight": 836
  },
  {
    "source": "twitter",
    "id": "1240605130589982720",
    "username": "oulipia",
    "likes": 2,
    "originalImage": "https://pbs.twimg.com/media/ETeDxgPX0AM80xK.jpg",
    "avatarImage": "https://pbs.twimg.com/profile_images/1075459102996869120/PApjLwz__normal.jpg",
    "date": "2020-03-19T12:44:47.000+01:00",
    "imageWidth": 1200,
    "imageHeight": 644
  },
  {
    "source": "twitter",
    "id": "1240597938872729600",
    "username": "TheJurisGeek",
    "likes": 2,
    "originalImage": "https://pbs.twimg.com/media/ETd9PxyXkAAJiso.jpg",
    "avatarImage": "https://pbs.twimg.com/profile_images/1202213416464723970/QoMG06QU_normal.jpg",
    "date": "2020-03-19T12:16:12.000+01:00",
    "imageWidth": 1080,
    "imageHeight": 607
  },
  {
    "source": "twitter",
    "id": "1240668767035830273",
    "username": "TogIllustration",
    "likes": 1,
    "originalImage": "https://pbs.twimg.com/media/ETe9p2dWkAMCqbS.jpg",
    "avatarImage": "https://pbs.twimg.com/profile_images/1051888582795898883/U0VeseZS_normal.jpg",
    "date": "2020-03-19T16:57:39.000+01:00",
    "imageWidth": 1200,
    "imageHeight": 725
  },
  {
    "source": "twitter",
    "id": "1240646803093151744",
    "username": "fredfactory",
    "likes": 1,
    "originalImage": "https://pbs.twimg.com/media/ETepk-4WoAY4SQ6.jpg",
    "avatarImage": "https://pbs.twimg.com/profile_images/1239308951033974787/LY4KWR3f_normal.jpg",
    "date": "2020-03-19T15:30:22.000+01:00",
    "imageWidth": 1200,
    "imageHeight": 826
  },
  {
    "source": "twitter",
    "id": "1240605221681799171",
    "username": "Chmanometre",
    "likes": 1,
    "originalImage": "https://pbs.twimg.com/media/ETeDoeAWAAAjudP.jpg",
    "avatarImage": "https://pbs.twimg.com/profile_images/837781651400818689/-T_Z10SJ_normal.jpg",
    "date": "2020-03-19T12:45:08.000+01:00",
    "imageWidth": 1029,
    "imageHeight": 708
  },
  {
    "source": "twitter",
    "id": "1240560032686780416",
    "username": "AurelieCorvisy",
    "likes": 1,
    "originalImage": "https://pbs.twimg.com/media/ETdaxWRXsAALsPA.jpg",
    "avatarImage": "https://pbs.twimg.com/profile_images/1137314475193905153/D8Q8WV1x_normal.jpg",
    "date": "2020-03-19T09:45:34.000+01:00",
    "imageWidth": 1053,
    "imageHeight": 667
  },
  {
    "source": "twitter",
    "id": "1240482923259854849",
    "username": "anniedwyer924",
    "likes": 1,
    "originalImage": "https://pbs.twimg.com/media/ETcUpFrX0AIOzWc.jpg",
    "avatarImage": "https://pbs.twimg.com/profile_images/1238314767972020224/J2ImGG28_normal.jpg",
    "date": "2020-03-19T04:39:10.000+01:00",
    "imageWidth": 1122,
    "imageHeight": 772
  },
  {
    "source": "twitter",
    "id": "1240685863815663616",
    "username": "MorineB1",
    "likes": 0,
    "originalImage": "https://pbs.twimg.com/media/ETfNBqNWsAI3XjI.jpg",
    "avatarImage": "https://pbs.twimg.com/profile_images/1239594045648797703/iNZfkWZ-_normal.jpg",
    "date": "2020-03-19T18:05:35.000+01:00",
    "imageWidth": 1199,
    "imageHeight": 645
  },
  {
    "source": "twitter",
    "id": "1240677209389649924",
    "username": "HaudeFun",
    "likes": 0,
    "originalImage": "https://pbs.twimg.com/media/ETfFGyGXQAItgVo.jpg",
    "avatarImage": "https://pbs.twimg.com/profile_images/1240677493251747847/Kgi-AwwF_normal.jpg",
    "date": "2020-03-19T17:31:12.000+01:00",
    "imageWidth": 1006,
    "imageHeight": 541
  },
  {
    "source": "twitter",
    "id": "1240675008671817729",
    "username": "TestonC",
    "likes": 0,
    "originalImage": "https://pbs.twimg.com/media/ETfDVgMX0AEb8bv.jpg",
    "avatarImage": "https://pbs.twimg.com/profile_images/3096055790/ed4f6f21436a031cf5716fbb4e4eca6c_normal.jpeg",
    "date": "2020-03-19T17:22:27.000+01:00",
    "imageWidth": 1200,
    "imageHeight": 900
  },
  {
    "source": "twitter",
    "id": "1240656639579095040",
    "username": "Bakine51",
    "likes": 0,
    "originalImage": "https://pbs.twimg.com/media/ETeyn3UXkAAU-f5.jpg",
    "avatarImage": "https://pbs.twimg.com/profile_images/1207393893756686337/7k122-4H_normal.jpg",
    "date": "2020-03-19T16:09:27.000+01:00",
    "imageWidth": 1200,
    "imageHeight": 638
  },
  {
    "source": "twitter",
    "id": "1240662489592926209",
    "username": "MHMtemmuz",
    "likes": 0,
    "originalImage": "https://pbs.twimg.com/media/ETe3xmOXYAMC7cb.jpg",
    "avatarImage": "https://pbs.twimg.com/profile_images/929303112409640960/yw4PzAQ7_normal.jpg",
    "date": "2020-03-19T16:32:42.000+01:00",
    "imageWidth": 1200,
    "imageHeight": 900
  },
  {
    "source": "twitter",
    "id": "1240651197872300032",
    "username": "mrsgwennie",
    "likes": 0,
    "originalImage": "https://pbs.twimg.com/media/ETetrDdX0AAO9Mp.jpg",
    "avatarImage": "https://pbs.twimg.com/profile_images/2378810343/fqbeksq3a43ez59ls31o_normal.jpeg",
    "date": "2020-03-19T15:47:50.000+01:00",
    "imageWidth": 1200,
    "imageHeight": 900
  },
  {
    "source": "twitter",
    "id": "1240604826838409217",
    "username": "oulipia",
    "likes": 0,
    "originalImage": "https://pbs.twimg.com/media/ETeDb1aWoAARsmh.jpg",
    "avatarImage": "https://pbs.twimg.com/profile_images/1075459102996869120/PApjLwz__normal.jpg",
    "date": "2020-03-19T12:43:34.000+01:00",
    "imageWidth": 1200,
    "imageHeight": 675
  },
  {
    "source": "twitter",
    "id": "1240597614149750785",
    "username": "lynn82713013",
    "likes": 0,
    "originalImage": "https://pbs.twimg.com/media/ETd886aXkAA9oVh.jpg",
    "avatarImage": "https://abs.twimg.com/sticky/default_profile_images/default_profile_normal.png",
    "date": "2020-03-19T12:14:55.000+01:00",
    "imageWidth": 1200,
    "imageHeight": 900
  }
]